ezslack/__init__.py
ezslack/app.py
ezslack/handler/__init__.py
ezslack/handler/handler.py
ezslack/handler/registry.py
ezslack/request/__init__.py
ezslack/request/action.py
ezslack/request/base.py
ezslack/request/message.py
ezslack/request/view_closed.py
ezslack/request/view_submission.py
ezslack-0.1.2.dist-info/LICENSE
ezslack-0.1.2.dist-info/METADATA
ezslack-0.1.2.dist-info/WHEEL
ezslack-0.1.2.dist-info/top_level.txt
ezslack-0.1.2.dist-info/RECORD
