Metadata-Version: 2.1
Name: ezslack
Version: 0.1.2
Summary: Easy Slack framework wrapping Bolt for Python
Home-page: https://github.com/taekop/ezslack
Author: taekop
Author-email: taekop@naver.com
License: MIT
Keywords: slack
Classifier: Programming Language :: Python :: 3
Classifier: License :: OSI Approved :: MIT License
Classifier: Operating System :: OS Independent
Requires-Python: >=3.9,<4.0
License-File: LICENSE
Requires-Dist: slack-bolt (>=1.18.0)
Requires-Dist: slack-sdk (>=3.27.0)
